Metadata-Version: 1.0
Name: dcom
Version: 0.0.4
Summary: dcom
Home-page: https://github.com/emre/dcom
Author: Emre Yilmaz
Author-email: mail@emreyilmaz.me
License: MIT
Platform: UNKNOWN
